nobubo/.gitignore
nobubo/__init__.py
nobubo/__main__.py
nobubo/assembly.py
nobubo/cli.py
nobubo/disassembly.py
nobubo/errors.py
nobubo/init_nobubo.py
nobubo-1.6.0.dist-info/LICENSE
nobubo-1.6.0.dist-info/METADATA
nobubo-1.6.0.dist-info/WHEEL
nobubo-1.6.0.dist-info/entry_points.txt
nobubo-1.6.0.dist-info/RECORD
