Metadata-Version: 2.3
Name: nobubo
Version: 1.6.0
Summary: Nobubo assembles a digital pdf sewing pattern and cuts it up into a desired output print size. A specialized n-up tool also suited for non-sewing purposes.
License: AGPL v3.0
Author: bytinbit
Requires-Python: >=3.11
Classifier: Topic :: Printing
Classifier: Topic :: Utilities
Classifier: Topic :: Multimedia :: Graphics :: Graphics Conversion
Classifier: License :: OSI Approved :: GNU Affero General Public License v3
Requires-Dist: click (>=8.1.3)
Requires-Dist: pikepdf (>=9.4.2)
